MANIFEST.in
README.md
flask_blitzdb.py
setup.py
flask_blitzdb.egg-info/PKG-INFO
flask_blitzdb.egg-info/SOURCES.txt
flask_blitzdb.egg-info/dependency_links.txt
flask_blitzdb.egg-info/not-zip-safe
flask_blitzdb.egg-info/requires.txt
flask_blitzdb.egg-info/top_level.txt
test/test_model.py
test/tests.py