Metadata-Version: 1.1
Name: flask-blitzdb
Version: 0.1
Summary: Flask extension for blitzdb
Home-page: https://github.com/puredistortion/flask-blitzdb
Author: Dale Stirling
Author-email: feedback@puredistortion.com
License: UNKNOWN
Platform: any
Classifier: Environment :: Web Environment
Classifier: Intended Audience :: Developers
Classifier: Intended Audience :: Information Technology
Classifier: Operating System :: OS Independent
Classifier: Programming Language :: Python
Classifier: Topic :: Internet :: WWW/HTTP :: Dynamic Content
Classifier: Topic :: Database :: Front-Ends
Classifier: Topic :: Software Development :: Libraries :: Python Modules
Classifier: Topic :: Internet :: WWW/HTTP :: WSGI :: Middleware
